buildingmotif/__init__.py
buildingmotif/api/Dockerfile
buildingmotif/api/__init__.py
buildingmotif/api/app.py
buildingmotif/api/serializers/library.py
buildingmotif/api/serializers/model.py
buildingmotif/api/serializers/parser.py
buildingmotif/api/serializers/template.py
buildingmotif/api/start.sh
buildingmotif/api/views/__init__.py
buildingmotif/api/views/library.py
buildingmotif/api/views/model.py
buildingmotif/api/views/parser.py
buildingmotif/api/views/template.py
buildingmotif/bin/cli.py
buildingmotif/building_motif/__init__.py
buildingmotif/building_motif/building_motif.py
buildingmotif/building_motif/singleton.py
buildingmotif/database/__init__.py
buildingmotif/database/errors.py
buildingmotif/database/graph_connection.py
buildingmotif/database/table_connection.py
buildingmotif/database/tables.py
buildingmotif/database/utils.py
buildingmotif/dataclasses/__init__.py
buildingmotif/dataclasses/compiled_model.py
buildingmotif/dataclasses/library.py
buildingmotif/dataclasses/model.py
buildingmotif/dataclasses/shape_collection.py
buildingmotif/dataclasses/template.py
buildingmotif/dataclasses/validation.py
buildingmotif/ingresses/__init__.py
buildingmotif/ingresses/bacnet.py
buildingmotif/ingresses/base.py
buildingmotif/ingresses/brick.py
buildingmotif/ingresses/csvingress.py
buildingmotif/ingresses/naming_convention.py
buildingmotif/ingresses/template.py
buildingmotif/ingresses/xlsx.py
buildingmotif/label_parsing/__init__.py
buildingmotif/label_parsing/combinators.py
buildingmotif/label_parsing/parser.py
buildingmotif/label_parsing/tokens.py
buildingmotif/libraries/__init__.py
buildingmotif/libraries/bacnet/brick.yml
buildingmotif/libraries/brick/Brick.ttl
buildingmotif/libraries/constraints/constraints.ttl
buildingmotif/model_builder.py
buildingmotif/namespaces.py
buildingmotif/resources/building_motif_ontology.ttl
buildingmotif/resources/libraries.default.yml
buildingmotif/schemas.py
buildingmotif/shape_builder/__init__.py
buildingmotif/shape_builder/shape.py
buildingmotif-0.4.0.dist-info/LICENSE
buildingmotif-0.4.0.dist-info/METADATA
buildingmotif-0.4.0.dist-info/WHEEL
buildingmotif-0.4.0.dist-info/entry_points.txt
buildingmotif-0.4.0.dist-info/RECORD
