Metadata-Version: 2.1
Name: buildingmotif
Version: 0.4.0
Summary: Building Metadata OnTology Interoperability Framework
Home-page: https://github.com/NREL/BuildingMOTIF
License: LICENSE
Author: Hannah Eslinger
Author-email: Hannah.Eslinger@nrel.gov
Requires-Python: >=3.10,<3.13
Classifier: License :: Other/Proprietary License
Classifier: Programming Language :: Python :: 3
Classifier: Programming Language :: Python :: 3.10
Classifier: Programming Language :: Python :: 3.11
Provides-Extra: all
Provides-Extra: all-ingresses
Provides-Extra: bacnet-ingress
Provides-Extra: postgres
Provides-Extra: topquadrant
Provides-Extra: xlsx-ingress
Requires-Dist: Flask (>=2.1.2,<3.0.0)
Requires-Dist: Flask-API (>=3.0.post1,<4.0)
Requires-Dist: SQLAlchemy[mypy] (>=1.4.44,<2.0.0)
Requires-Dist: alembic (>=1.8.0,<2.0.0)
Requires-Dist: brick-tq-shacl (==0.3.4a2) ; extra == "topquadrant"
Requires-Dist: jsonschema (>=4.21.1,<5.0.0)
Requires-Dist: matplotlib (>=3.9.2,<4.0.0)
Requires-Dist: nbmake (>=1.3.0,<2.0.0)
Requires-Dist: networkx (>=3.4.2,<4.0.0)
Requires-Dist: pandas (>=2.2.3,<3.0.0)
Requires-Dist: psycopg2 (>=2.9.5,<3.0.0) ; extra == "all" or extra == "postgres"
Requires-Dist: pyaml (>=21.10.1,<22.0.0)
Requires-Dist: pygit2 (>=1.17,<1.18)
Requires-Dist: pyshacl (>=0.30,<0.31)
Requires-Dist: rdflib (>=7.0)
Requires-Dist: rdflib-sqlalchemy (>=0.5.3,<0.6.0)
Requires-Dist: rfc3987 (>=1.3.8,<2.0.0)
Requires-Dist: setuptools (>=73.0.1,<74.0.0)
Requires-Dist: types-PyYAML (>=6.0.4,<7.0.0)
Requires-Dist: types-jsonschema (>=4.21.0.20240311,<5.0.0.0)
Requires-Dist: werkzeug (>=2.3.7,<3.0.0)
Project-URL: Documentation, https://buildingmotif.readthedocs.io/
Project-URL: Repository, https://github.com/NREL/BuildingMOTIF
